{
  "armorSetName": "wisdon",
  "performanceMode": true,
  "head": {
    "itemKey": "extraarmor:lapis_helmet"
  },
  "chest": {
    "itemKey": "extraarmor:lapis_chestplate"
  },
  "legs": {
    "itemKey": "extraarmor:lapis_leggings"
  },
  "boots": {
    "itemKey": "extraarmor:lapis_boots"
  },
  "additionalSetPieces": [
    {
    "itemKey": "meetyourfight:blossoming_mind"
    },
    {
    "itemKey": "nameless_trinkets:experience_battery"
    }
  ],
  "hideGeneratedTooltip": true,
  "fullSetBonuses": [
    {
      "type": "effect",
      "name": "goety:insight",
      "value": 2.0,
      "interactionType": "self",
      "interactionDuration": 300
    }
  ]
}